hiero_sdk_python-0.1.10.dist-info/METADATA
hiero_sdk_python-0.1.10.dist-info/WHEEL
hiero_sdk_python-0.1.10.dist-info/entry_points.txt
hiero_sdk_python-0.1.10.dist-info/licenses/LICENSE
hiero_sdk_python/Duration.py
hiero_sdk_python/__init__.py
hiero_sdk_python/account/__init__.py
hiero_sdk_python/account/account_allowance_approve_transaction.py
hiero_sdk_python/account/account_allowance_delete_transaction.py
hiero_sdk_python/account/account_balance.py
hiero_sdk_python/account/account_create_transaction.py
hiero_sdk_python/account/account_delete_transaction.py
hiero_sdk_python/account/account_id.py
hiero_sdk_python/account/account_info.py
hiero_sdk_python/account/account_records_query.py
hiero_sdk_python/account/account_update_transaction.py
hiero_sdk_python/address_book/endpoint.py
hiero_sdk_python/address_book/node_address.py
hiero_sdk_python/channels.py
hiero_sdk_python/client/__init__.py
hiero_sdk_python/client/client.py
hiero_sdk_python/client/network.py
hiero_sdk_python/consensus/__init__.py
hiero_sdk_python/consensus/topic_create_transaction.py
hiero_sdk_python/consensus/topic_delete_transaction.py
hiero_sdk_python/consensus/topic_id.py
hiero_sdk_python/consensus/topic_info.py
hiero_sdk_python/consensus/topic_message.py
hiero_sdk_python/consensus/topic_message_submit_transaction.py
hiero_sdk_python/consensus/topic_update_transaction.py
hiero_sdk_python/contract/contract_bytecode_query.py
hiero_sdk_python/contract/contract_call_query.py
hiero_sdk_python/contract/contract_create_transaction.py
hiero_sdk_python/contract/contract_delete_transaction.py
hiero_sdk_python/contract/contract_execute_transaction.py
hiero_sdk_python/contract/contract_function_parameters.py
hiero_sdk_python/contract/contract_function_parameters.pyi
hiero_sdk_python/contract/contract_function_result.py
hiero_sdk_python/contract/contract_id.py
hiero_sdk_python/contract/contract_info.py
hiero_sdk_python/contract/contract_info_query.py
hiero_sdk_python/contract/contract_log_info.py
hiero_sdk_python/contract/contract_nonce_info.py
hiero_sdk_python/contract/contract_update_transaction.py
hiero_sdk_python/contract/ethereum_transaction.py
hiero_sdk_python/crypto/__init__.py
hiero_sdk_python-0.1.10.dist-info/RECORD
