Metadata-Version: 2.1
Name: hiero-sdk-python
Version: 0.1.10
Summary: A Hiero SDK in pure Python
Author-Email: Nadine Loepfe <nadine.loepfe@hashgraph.com>, Richard Bair <rbair23@users.noreply.github.com>
Maintainer-Email: Nadine Loepfe <nadine.loepfe@hashgraph.com>, Sophie Bulloch <exploreriii57@gmail.com>
License:                                  Apache License
Classifier: Development Status :: 2 - Pre-Alpha
Classifier: License :: OSI Approved :: Apache Software License
Classifier: Programming Language :: Python :: 3.10
Classifier: Programming Language :: Python :: 3.11
Classifier: Programming Language :: Python :: 3.12
Classifier: Programming Language :: Python :: 3.13
Classifier: Operating System :: OS Independent
Classifier: Intended Audience :: Developers
Classifier: Topic :: Software Development :: Libraries :: Python Modules
Requires-Python: <3.14,>=3.10
Requires-Dist: grpcio-tools==1.76.0
Requires-Dist: protobuf==6.33.1
Requires-Dist: grpcio==1.76.0
Requires-Dist: cryptography==44.0.0
Requires-Dist: python-dotenv==1.2.1
Requires-Dist: requests==2.32.3
Requires-Dist: pycryptodome==3.23.0
Requires-Dist: eth-abi==5.2.0
Requires-Dist: rlp>=4.0.0
Requires-Dist: eth-keys==0.7.0
